sql2mermaid/__init__.py
sql2mermaid/dependencies.py
sql2mermaid/main.py
sql2mermaid/tables.py
sql2mermaid/utils.py
sql2mermaid-2.2.1.dist-info/LICENSE.md
sql2mermaid-2.2.1.dist-info/METADATA
sql2mermaid-2.2.1.dist-info/WHEEL
sql2mermaid-2.2.1.dist-info/RECORD
