Metadata-Version: 2.3
Name: sql2mermaid
Version: 2.2.1
Summary: Convert SQL table dependencies to mermaid.js
License: MIT
Author: nkato
Author-email: naokato.aq@gmail.com
Requires-Python: >=3.9.0,<4.0.0
Classifier: License :: OSI Approved :: MIT License
Classifier: Programming Language :: Python :: 3
Classifier: Programming Language :: Python :: 3.9
Classifier: Programming Language :: Python :: 3.10
Classifier: Programming Language :: Python :: 3.11
Classifier: Programming Language :: Python :: 3.12
Classifier: Programming Language :: Python :: 3.13
Requires-Dist: sqlparse (>=0.4.3,<0.5.0)
Project-URL: Repository, https://github.com/nkato/sql2mermaid
